whalegistic/__init__.py
whalegistic/whalegistic.py
whalegistic-0.1.6.dist-info/.DS_Store
whalegistic-0.1.6.dist-info/METADATA
whalegistic-0.1.6.dist-info/WHEEL
whalegistic-0.1.6.dist-info/top_level.txt
whalegistic-0.1.6.dist-info/RECORD
